pygenal/__init__.py
pygenal/ga.py
pygenal/test.py
pygenal-1.0.7.dist-info/LICENSE
pygenal-1.0.7.dist-info/METADATA
pygenal-1.0.7.dist-info/WHEEL
pygenal-1.0.7.dist-info/top_level.txt
pygenal-1.0.7.dist-info/RECORD
