Metadata-Version: 2.1
Name: pygenal
Version: 1.0.7
Summary: Python implementation of Genetic Algorithm
Home-page: https://github.com/themladypan/pyga
Author: Stanislav Rubint
Author-email: stanislav@rubint.sk
License: UNKNOWN
Platform: UNKNOWN
Classifier: Programming Language :: Python :: 3
Classifier: License :: OSI Approved :: MIT License
Classifier: Operating System :: Unix
Requires-Python: >=3.6
